zirpu/__init__.py
zirpu/time.py
zirpu_utils-1.0.0.dist-info/LICENSE
zirpu_utils-1.0.0.dist-info/METADATA
zirpu_utils-1.0.0.dist-info/WHEEL
zirpu_utils-1.0.0.dist-info/entry_points.txt
zirpu_utils-1.0.0.dist-info/top_level.txt
zirpu_utils-1.0.0.dist-info/RECORD
