Metadata-Version: 2.1
Name: zirpu-utils
Version: 1.0.0
Summary: Zirpu's Misc. Utilities.
Home-page: http://blahg.zirpu.org
Author: Allan Bailey
Author-email: allan@zirpu.org
License: UNKNOWN
Platform: UNKNOWN
Classifier: Development Status :: 4 - Beta
Classifier: Environment :: Console
Classifier: License :: OSI Approved :: MIT License
Classifier: Programming Language :: Python :: 3.6
Classifier: Programming Language :: Python :: 3.7
Classifier: Operating System :: POSIX :: Linux
Classifier: Topic :: Utilities
Requires-Dist: ipython
Requires-Dist: jupyter
Requires-Dist: python-baseconv
Requires-Dist: tmuxp
Requires-Dist: twine
